{
  "metadata": {
    "topic": "Non Verbal Reasoning",
    "subtopic": "water_images",
    "total_questions": 20,
    "sources": [
      "IndiaBIX"
    ],
    "last_updated": "2026-05-18"
  },
  "questions": [
    {
      "id": "reasoning_wateri_001",
      "topic": "reasoning",
      "subtopic": "water_images",
      "difficulty": "medium",
      "company_tags": [
        "TCS",
        "Infosys",
        "Wipro",
        "Accenture"
      ],
      "question": "Choose the alternative which is closely resembles the water-image of the given combination.",
      "options": [
        "1",
        "2",
        "3",
        "4"
      ],
      "answer": "D",
      "explanation": "No answer description is available. <a class=\"text-link\" href=\"https://www.indiabix.com/non-verbal-reasoning/water-images/discussion-420#comments\"> Let's discuss.</a>",
      "shortcut": "Visual reasoning: observe the figure carefully, identify the pattern or transformation being tested",
      "formula_used": "",
      "trap_type": "Not accounting for rotation, reflection, or perspective changes correctly",
      "source": "IndiaBIX",
      "source_url": "https://www.indiabix.com/non-verbal-reasoning/water-images/",
      "pattern_detected": "",
      "image_url": "/images/reasoning/water_images/6.png"
    },
    {
      "id": "reasoning_wateri_002",
      "topic": "reasoning",
      "subtopic": "water_images",
      "difficulty": "medium",
      "company_tags": [
        "TCS",
        "Infosys",
        "Wipro",
        "Accenture"
      ],
      "question": "Choose the alternative which is closely resembles the water-image of the given combination.",
      "options": [
        "1",
        "2",
        "3",
        "4"
      ],
      "answer": "B",
      "explanation": "No answer description is available. <a class=\"text-link\" href=\"https://www.indiabix.com/non-verbal-reasoning/water-images/discussion-434#comments\"> Let's discuss.</a>",
      "shortcut": "Visual reasoning: observe the figure carefully, identify the pattern or transformation being tested",
      "formula_used": "",
      "trap_type": "Not accounting for rotation, reflection, or perspective changes correctly",
      "source": "IndiaBIX",
      "source_url": "https://www.indiabix.com/non-verbal-reasoning/water-images/",
      "pattern_detected": "",
      "image_url": "/images/reasoning/water_images/20.png"
    },
    {
      "id": "reasoning_wateri_003",
      "topic": "reasoning",
      "subtopic": "water_images",
      "difficulty": "medium",
      "company_tags": [
        "TCS",
        "Infosys",
        "Wipro",
        "Accenture"
      ],
      "question": "Choose the alternative which is closely resembles the water-image of the given combination.",
      "options": [
        "1",
        "2",
        "3",
        "4"
      ],
      "answer": "C",
      "explanation": "No answer description is available. <a class=\"text-link\" href=\"https://www.indiabix.com/non-verbal-reasoning/water-images/discussion-429#comments\"> Let's discuss.</a>",
      "shortcut": "Visual reasoning: observe the figure carefully, identify the pattern or transformation being tested",
      "formula_used": "",
      "trap_type": "Not accounting for rotation, reflection, or perspective changes correctly",
      "source": "IndiaBIX",
      "source_url": "https://www.indiabix.com/non-verbal-reasoning/water-images/",
      "pattern_detected": "",
      "image_url": "/images/reasoning/water_images/15.png"
    },
    {
      "id": "reasoning_wateri_004",
      "topic": "reasoning",
      "subtopic": "water_images",
      "difficulty": "medium",
      "company_tags": [
        "TCS",
        "Infosys",
        "Wipro",
        "Accenture"
      ],
      "question": "Choose the alternative which is closely resembles the water-image of the given combination.",
      "options": [
        "1",
        "2",
        "3",
        "4"
      ],
      "answer": "C",
      "explanation": "No answer description is available. <a class=\"text-link\" href=\"https://www.indiabix.com/non-verbal-reasoning/water-images/discussion-437#comments\"> Let's discuss.</a>",
      "shortcut": "Visual reasoning: observe the figure carefully, identify the pattern or transformation being tested",
      "formula_used": "",
      "trap_type": "Not accounting for rotation, reflection, or perspective changes correctly",
      "source": "IndiaBIX",
      "source_url": "https://www.indiabix.com/non-verbal-reasoning/water-images/",
      "pattern_detected": "",
      "image_url": "/images/reasoning/water_images/23.png"
    },
    {
      "id": "reasoning_wateri_005",
      "topic": "reasoning",
      "subtopic": "water_images",
      "difficulty": "medium",
      "company_tags": [
        "TCS",
        "Infosys",
        "Wipro",
        "Accenture"
      ],
      "question": "Choose the alternative which is closely resembles the water-image of the given combination.",
      "options": [
        "1",
        "2",
        "3",
        "4"
      ],
      "answer": "D",
      "explanation": "No answer description is available. <a class=\"text-link\" href=\"https://www.indiabix.com/non-verbal-reasoning/water-images/discussion-438#comments\"> Let's discuss.</a>",
      "shortcut": "Visual reasoning: observe the figure carefully, identify the pattern or transformation being tested",
      "formula_used": "",
      "trap_type": "Not accounting for rotation, reflection, or perspective changes correctly",
      "source": "IndiaBIX",
      "source_url": "https://www.indiabix.com/non-verbal-reasoning/water-images/",
      "pattern_detected": "",
      "image_url": "/images/reasoning/water_images/24.png"
    },
    {
      "id": "reasoning_wateri_006",
      "topic": "reasoning",
      "subtopic": "water_images",
      "difficulty": "medium",
      "company_tags": [
        "TCS",
        "Infosys",
        "Wipro",
        "Accenture"
      ],
      "question": "Choose the alternative which is closely resembles the water-image of the given combination.",
      "options": [
        "1",
        "2",
        "3",
        "4"
      ],
      "answer": "B",
      "explanation": "No answer description is available. <a class=\"text-link\" href=\"https://www.indiabix.com/non-verbal-reasoning/water-images/discussion-439#comments\"> Let's discuss.</a>",
      "shortcut": "Visual reasoning: observe the figure carefully, identify the pattern or transformation being tested",
      "formula_used": "",
      "trap_type": "Not accounting for rotation, reflection, or perspective changes correctly",
      "source": "IndiaBIX",
      "source_url": "https://www.indiabix.com/non-verbal-reasoning/water-images/011002",
      "pattern_detected": "",
      "image_url": "/images/reasoning/water_images/25.png"
    },
    {
      "id": "reasoning_wateri_007",
      "topic": "reasoning",
      "subtopic": "water_images",
      "difficulty": "medium",
      "company_tags": [
        "TCS",
        "Infosys",
        "Wipro",
        "Accenture"
      ],
      "question": "Choose the alternative which is closely resembles the water-image of the given combination.",
      "options": [
        "1",
        "2",
        "3",
        "4"
      ],
      "answer": "B",
      "explanation": "No answer description is available. <a class=\"text-link\" href=\"https://www.indiabix.com/non-verbal-reasoning/water-images/discussion-418#comments\"> Let's discuss.</a>",
      "shortcut": "Visual reasoning: observe the figure carefully, identify the pattern or transformation being tested",
      "formula_used": "",
      "trap_type": "Not accounting for rotation, reflection, or perspective changes correctly",
      "source": "IndiaBIX",
      "source_url": "https://www.indiabix.com/non-verbal-reasoning/water-images/011002",
      "pattern_detected": "",
      "image_url": "/images/reasoning/water_images/4.png"
    },
    {
      "id": "reasoning_wateri_008",
      "topic": "reasoning",
      "subtopic": "water_images",
      "difficulty": "medium",
      "company_tags": [
        "TCS",
        "Infosys",
        "Wipro",
        "Accenture"
      ],
      "question": "Choose the alternative which is closely resembles the water-image of the given combination.",
      "options": [
        "1",
        "2",
        "3",
        "4"
      ],
      "answer": "D",
      "explanation": "No answer description is available. <a class=\"text-link\" href=\"https://www.indiabix.com/non-verbal-reasoning/water-images/discussion-431#comments\"> Let's discuss.</a>",
      "shortcut": "Visual reasoning: observe the figure carefully, identify the pattern or transformation being tested",
      "formula_used": "",
      "trap_type": "Not accounting for rotation, reflection, or perspective changes correctly",
      "source": "IndiaBIX",
      "source_url": "https://www.indiabix.com/non-verbal-reasoning/water-images/011002",
      "pattern_detected": "",
      "image_url": "/images/reasoning/water_images/17.png"
    },
    {
      "id": "reasoning_wateri_009",
      "topic": "reasoning",
      "subtopic": "water_images",
      "difficulty": "medium",
      "company_tags": [
        "TCS",
        "Infosys",
        "Wipro",
        "Accenture"
      ],
      "question": "Choose the alternative which is closely resembles the water-image of the given combination.",
      "options": [
        "1",
        "2",
        "3",
        "4"
      ],
      "answer": "B",
      "explanation": "No answer description is available. <a class=\"text-link\" href=\"https://www.indiabix.com/non-verbal-reasoning/water-images/discussion-417#comments\"> Let's discuss.</a>",
      "shortcut": "Visual reasoning: observe the figure carefully, identify the pattern or transformation being tested",
      "formula_used": "",
      "trap_type": "Not accounting for rotation, reflection, or perspective changes correctly",
      "source": "IndiaBIX",
      "source_url": "https://www.indiabix.com/non-verbal-reasoning/water-images/011002",
      "pattern_detected": "",
      "image_url": "/images/reasoning/water_images/3.png"
    },
    {
      "id": "reasoning_wateri_010",
      "topic": "reasoning",
      "subtopic": "water_images",
      "difficulty": "medium",
      "company_tags": [
        "TCS",
        "Infosys",
        "Wipro",
        "Accenture"
      ],
      "question": "Choose the alternative which is closely resembles the water-image of the given combination.",
      "options": [
        "1",
        "2",
        "3",
        "4"
      ],
      "answer": "A",
      "explanation": "No answer description is available. <a class=\"text-link\" href=\"https://www.indiabix.com/non-verbal-reasoning/water-images/discussion-421#comments\"> Let's discuss.</a>",
      "shortcut": "Visual reasoning: observe the figure carefully, identify the pattern or transformation being tested",
      "formula_used": "",
      "trap_type": "Not accounting for rotation, reflection, or perspective changes correctly",
      "source": "IndiaBIX",
      "source_url": "https://www.indiabix.com/non-verbal-reasoning/water-images/011002",
      "pattern_detected": "",
      "image_url": "/images/reasoning/water_images/7.png"
    },
    {
      "id": "reasoning_wateri_011",
      "topic": "reasoning",
      "subtopic": "water_images",
      "difficulty": "medium",
      "company_tags": [
        "TCS",
        "Infosys",
        "Wipro",
        "Accenture"
      ],
      "question": "Choose the alternative which is closely resembles the water-image of the given combination.",
      "options": [
        "1",
        "2",
        "3",
        "4"
      ],
      "answer": "D",
      "explanation": "No answer description is available. <a class=\"text-link\" href=\"https://www.indiabix.com/non-verbal-reasoning/water-images/discussion-430#comments\"> Let's discuss.</a>",
      "shortcut": "Visual reasoning: observe the figure carefully, identify the pattern or transformation being tested",
      "formula_used": "",
      "trap_type": "Not accounting for rotation, reflection, or perspective changes correctly",
      "source": "IndiaBIX",
      "source_url": "https://www.indiabix.com/non-verbal-reasoning/water-images/011005",
      "pattern_detected": "",
      "image_url": "/images/reasoning/water_images/16.png"
    },
    {
      "id": "reasoning_wateri_012",
      "topic": "reasoning",
      "subtopic": "water_images",
      "difficulty": "medium",
      "company_tags": [
        "TCS",
        "Infosys",
        "Wipro",
        "Accenture"
      ],
      "question": "Choose the alternative which is closely resembles the water-image of the given combination.",
      "options": [
        "1",
        "2",
        "3",
        "4"
      ],
      "answer": "A",
      "explanation": "No answer description is available. <a class=\"text-link\" href=\"https://www.indiabix.com/non-verbal-reasoning/water-images/discussion-432#comments\"> Let's discuss.</a>",
      "shortcut": "Visual reasoning: observe the figure carefully, identify the pattern or transformation being tested",
      "formula_used": "",
      "trap_type": "Not accounting for rotation, reflection, or perspective changes correctly",
      "source": "IndiaBIX",
      "source_url": "https://www.indiabix.com/non-verbal-reasoning/water-images/011005",
      "pattern_detected": "",
      "image_url": "/images/reasoning/water_images/18.png"
    },
    {
      "id": "reasoning_wateri_013",
      "topic": "reasoning",
      "subtopic": "water_images",
      "difficulty": "medium",
      "company_tags": [
        "TCS",
        "Infosys",
        "Wipro",
        "Accenture"
      ],
      "question": "Choose the alternative which is closely resembles the water-image of the given combination.",
      "options": [
        "1",
        "2",
        "3",
        "4"
      ],
      "answer": "D",
      "explanation": "No answer description is available. <a class=\"text-link\" href=\"https://www.indiabix.com/non-verbal-reasoning/water-images/discussion-419#comments\"> Let's discuss.</a>",
      "shortcut": "Visual reasoning: observe the figure carefully, identify the pattern or transformation being tested",
      "formula_used": "",
      "trap_type": "Not accounting for rotation, reflection, or perspective changes correctly",
      "source": "IndiaBIX",
      "source_url": "https://www.indiabix.com/non-verbal-reasoning/water-images/011005",
      "pattern_detected": "",
      "image_url": "/images/reasoning/water_images/5.png"
    },
    {
      "id": "reasoning_wateri_014",
      "topic": "reasoning",
      "subtopic": "water_images",
      "difficulty": "medium",
      "company_tags": [
        "TCS",
        "Infosys",
        "Wipro",
        "Accenture"
      ],
      "question": "Choose the alternative which is closely resembles the water-image of the given combination.",
      "options": [
        "1",
        "2",
        "3",
        "4"
      ],
      "answer": "C",
      "explanation": "No answer description is available. <a class=\"text-link\" href=\"https://www.indiabix.com/non-verbal-reasoning/water-images/discussion-422#comments\"> Let's discuss.</a>",
      "shortcut": "Visual reasoning: observe the figure carefully, identify the pattern or transformation being tested",
      "formula_used": "",
      "trap_type": "Not accounting for rotation, reflection, or perspective changes correctly",
      "source": "IndiaBIX",
      "source_url": "https://www.indiabix.com/non-verbal-reasoning/water-images/011005",
      "pattern_detected": "",
      "image_url": "/images/reasoning/water_images/8.png"
    },
    {
      "id": "reasoning_wateri_015",
      "topic": "reasoning",
      "subtopic": "water_images",
      "difficulty": "medium",
      "company_tags": [
        "TCS",
        "Infosys",
        "Wipro",
        "Accenture"
      ],
      "question": "Choose the alternative which is closely resembles the water-image of the given combination.",
      "options": [
        "1",
        "2",
        "3",
        "4"
      ],
      "answer": "C",
      "explanation": "No answer description is available. <a class=\"text-link\" href=\"https://www.indiabix.com/non-verbal-reasoning/water-images/discussion-427#comments\"> Let's discuss.</a>",
      "shortcut": "Visual reasoning: observe the figure carefully, identify the pattern or transformation being tested",
      "formula_used": "",
      "trap_type": "Not accounting for rotation, reflection, or perspective changes correctly",
      "source": "IndiaBIX",
      "source_url": "https://www.indiabix.com/non-verbal-reasoning/water-images/011005",
      "pattern_detected": "",
      "image_url": "/images/reasoning/water_images/13.png"
    },
    {
      "id": "reasoning_wateri_016",
      "topic": "reasoning",
      "subtopic": "water_images",
      "difficulty": "medium",
      "company_tags": [
        "TCS",
        "Infosys",
        "Wipro",
        "Accenture"
      ],
      "question": "Choose the correct water image of the given figure (X) from amongst the four alternatives.",
      "options": [
        "1",
        "2",
        "3",
        "4"
      ],
      "answer": "B",
      "explanation": "No answer description is available. <a class=\"text-link\" href=\"https://www.indiabix.com/non-verbal-reasoning/water-images/discussion-443#comments\"> Let's discuss.</a>",
      "shortcut": "Visual reasoning: observe the figure carefully, identify the pattern or transformation being tested",
      "formula_used": "",
      "trap_type": "Not accounting for rotation, reflection, or perspective changes correctly",
      "source": "IndiaBIX",
      "source_url": "https://www.indiabix.com/non-verbal-reasoning/water-images/012001",
      "pattern_detected": "",
      "image_url": "/images/reasoning/water_images/4.png"
    },
    {
      "id": "reasoning_wateri_017",
      "topic": "reasoning",
      "subtopic": "water_images",
      "difficulty": "medium",
      "company_tags": [
        "TCS",
        "Infosys",
        "Wipro",
        "Accenture"
      ],
      "question": "Choose the correct water image of the given figure (X) from amongst the four alternatives.",
      "options": [
        "1",
        "2",
        "3",
        "4"
      ],
      "answer": "B",
      "explanation": "No answer description is available. <a class=\"text-link\" href=\"https://www.indiabix.com/non-verbal-reasoning/water-images/discussion-458#comments\"> Let's discuss.</a>",
      "shortcut": "Visual reasoning: observe the figure carefully, identify the pattern or transformation being tested",
      "formula_used": "",
      "trap_type": "Not accounting for rotation, reflection, or perspective changes correctly",
      "source": "IndiaBIX",
      "source_url": "https://www.indiabix.com/non-verbal-reasoning/water-images/012001",
      "pattern_detected": "",
      "image_url": "/images/reasoning/water_images/19.png"
    },
    {
      "id": "reasoning_wateri_018",
      "topic": "reasoning",
      "subtopic": "water_images",
      "difficulty": "medium",
      "company_tags": [
        "TCS",
        "Infosys",
        "Wipro",
        "Accenture"
      ],
      "question": "Choose the correct water image of the given figure (X) from amongst the four alternatives.",
      "options": [
        "1",
        "2",
        "3",
        "4"
      ],
      "answer": "D",
      "explanation": "No answer description is available. <a class=\"text-link\" href=\"https://www.indiabix.com/non-verbal-reasoning/water-images/discussion-453#comments\"> Let's discuss.</a>",
      "shortcut": "Visual reasoning: observe the figure carefully, identify the pattern or transformation being tested",
      "formula_used": "",
      "trap_type": "Not accounting for rotation, reflection, or perspective changes correctly",
      "source": "IndiaBIX",
      "source_url": "https://www.indiabix.com/non-verbal-reasoning/water-images/012001",
      "pattern_detected": "",
      "image_url": "/images/reasoning/water_images/14.png"
    },
    {
      "id": "reasoning_wateri_019",
      "topic": "reasoning",
      "subtopic": "water_images",
      "difficulty": "medium",
      "company_tags": [
        "TCS",
        "Infosys",
        "Wipro",
        "Accenture"
      ],
      "question": "Choose the correct water image of the given figure (X) from amongst the four alternatives.",
      "options": [
        "1",
        "2",
        "3",
        "4"
      ],
      "answer": "A",
      "explanation": "No answer description is available. <a class=\"text-link\" href=\"https://www.indiabix.com/non-verbal-reasoning/water-images/discussion-460#comments\"> Let's discuss.</a>",
      "shortcut": "Visual reasoning: observe the figure carefully, identify the pattern or transformation being tested",
      "formula_used": "",
      "trap_type": "Not accounting for rotation, reflection, or perspective changes correctly",
      "source": "IndiaBIX",
      "source_url": "https://www.indiabix.com/non-verbal-reasoning/water-images/012001",
      "pattern_detected": "",
      "image_url": "/images/reasoning/water_images/21.png"
    },
    {
      "id": "reasoning_wateri_020",
      "topic": "reasoning",
      "subtopic": "water_images",
      "difficulty": "medium",
      "company_tags": [
        "TCS",
        "Infosys",
        "Wipro",
        "Accenture"
      ],
      "question": "Choose the correct water image of the given figure (X) from amongst the four alternatives.",
      "options": [
        "1",
        "2",
        "3",
        "4"
      ],
      "answer": "C",
      "explanation": "No answer description is available. <a class=\"text-link\" href=\"https://www.indiabix.com/non-verbal-reasoning/water-images/discussion-449#comments\"> Let's discuss.</a>",
      "shortcut": "Visual reasoning: observe the figure carefully, identify the pattern or transformation being tested",
      "formula_used": "",
      "trap_type": "Not accounting for rotation, reflection, or perspective changes correctly",
      "source": "IndiaBIX",
      "source_url": "https://www.indiabix.com/non-verbal-reasoning/water-images/012001",
      "pattern_detected": "",
      "image_url": "/images/reasoning/water_images/10.png"
    }
  ]
}